<?xml version="1.0"?>
<!DOCTYPE hibernate-mapping PUBLIC "-//Hibernate/Hibernate Mapping DTD 3.0//EN" "http://hibernate.sourceforge.net/hibernate-mapping-3.0.dtd">

<hibernate-mapping auto-import="false" default-lazy="false">
	<import class="com.canal.etico.liferay.portlet.canal.manager.model.Accion" />
	<import class="com.canal.etico.liferay.portlet.canal.manager.model.Categoria" />
	<import class="com.canal.etico.liferay.portlet.canal.manager.model.Comp" />
	<import class="com.canal.etico.liferay.portlet.canal.manager.model.Comunicacion" />
	<import class="com.canal.etico.liferay.portlet.canal.manager.model.Denuncia" />
	<import class="com.canal.etico.liferay.portlet.canal.manager.model.DenunciaAccion" />
	<import class="com.canal.etico.liferay.portlet.canal.manager.model.Motivo" />
	<import class="com.canal.etico.liferay.portlet.canal.manager.model.Observacion" />
	<import class="com.canal.etico.liferay.portlet.canal.manager.model.UserCompany" />
	<import class="com.canal.etico.liferay.portlet.canal.manager.model.Vinculacion" />
	<class name="com.canal.etico.liferay.portlet.canal.manager.model.impl.AccionImpl" table="canal_etico_Accion">
		<id access="com.liferay.portal.dao.orm.hibernate.LiferayPropertyAccessor" name="accionId" type="long">
			<generator class="assigned" />
		</id>
		<property access="com.liferay.portal.dao.orm.hibernate.LiferayPropertyAccessor" name="compId" type="com.liferay.portal.dao.orm.hibernate.LongType" />
		<property access="com.liferay.portal.dao.orm.hibernate.LiferayPropertyAccessor" name="nombre" type="com.liferay.portal.dao.orm.hibernate.StringType" />
		<property access="com.liferay.portal.dao.orm.hibernate.LiferayPropertyAccessor" name="estado" type="com.liferay.portal.dao.orm.hibernate.LongType" />
		<property access="com.liferay.portal.dao.orm.hibernate.LiferayPropertyAccessor" name="activo" type="com.liferay.portal.dao.orm.hibernate.BooleanType" />
		<property access="com.liferay.portal.dao.orm.hibernate.LiferayPropertyAccessor" name="createDate" type="org.hibernate.type.TimestampType" />
		<property access="com.liferay.portal.dao.orm.hibernate.LiferayPropertyAccessor" name="modifiedDate" type="org.hibernate.type.TimestampType" />
	</class>
	<class name="com.canal.etico.liferay.portlet.canal.manager.model.impl.CategoriaImpl" table="canal_etico_Categoria">
		<id access="com.liferay.portal.dao.orm.hibernate.LiferayPropertyAccessor" name="categoriaId" type="long">
			<generator class="assigned" />
		</id>
		<property access="com.liferay.portal.dao.orm.hibernate.LiferayPropertyAccessor" name="compId" type="com.liferay.portal.dao.orm.hibernate.LongType" />
		<property access="com.liferay.portal.dao.orm.hibernate.LiferayPropertyAccessor" name="nombre" type="com.liferay.portal.dao.orm.hibernate.StringType" />
		<property access="com.liferay.portal.dao.orm.hibernate.LiferayPropertyAccessor" name="tipo" type="com.liferay.portal.dao.orm.hibernate.StringType" />
		<property access="com.liferay.portal.dao.orm.hibernate.LiferayPropertyAccessor" name="codigo" type="com.liferay.portal.dao.orm.hibernate.StringType" />
		<property access="com.liferay.portal.dao.orm.hibernate.LiferayPropertyAccessor" name="activo" type="com.liferay.portal.dao.orm.hibernate.BooleanType" />
		<property access="com.liferay.portal.dao.orm.hibernate.LiferayPropertyAccessor" name="createDate" type="org.hibernate.type.TimestampType" />
		<property access="com.liferay.portal.dao.orm.hibernate.LiferayPropertyAccessor" name="modifiedDate" type="org.hibernate.type.TimestampType" />
	</class>
	<class name="com.canal.etico.liferay.portlet.canal.manager.model.impl.CompImpl" table="canal_etico_Comp">
		<id access="com.liferay.portal.dao.orm.hibernate.LiferayPropertyAccessor" name="compId" type="long">
			<generator class="assigned" />
		</id>
		<property access="com.liferay.portal.dao.orm.hibernate.LiferayPropertyAccessor" name="suiteCompId" type="com.liferay.portal.dao.orm.hibernate.LongType" />
		<property access="com.liferay.portal.dao.orm.hibernate.LiferayPropertyAccessor" name="cif" type="com.liferay.portal.dao.orm.hibernate.StringType" />
		<property access="com.liferay.portal.dao.orm.hibernate.LiferayPropertyAccessor" name="name" type="com.liferay.portal.dao.orm.hibernate.StringType" />
		<property access="com.liferay.portal.dao.orm.hibernate.LiferayPropertyAccessor" name="description" type="com.liferay.portal.dao.orm.hibernate.StringType" />
		<property access="com.liferay.portal.dao.orm.hibernate.LiferayPropertyAccessor" name="observations" type="com.liferay.portal.dao.orm.hibernate.StringType" />
		<property access="com.liferay.portal.dao.orm.hibernate.LiferayPropertyAccessor" name="agreement" type="com.liferay.portal.dao.orm.hibernate.StringType" />
		<property access="com.liferay.portal.dao.orm.hibernate.LiferayPropertyAccessor" name="friendlyURL" type="com.liferay.portal.dao.orm.hibernate.StringType" />
		<property access="com.liferay.portal.dao.orm.hibernate.LiferayPropertyAccessor" name="logo" type="com.liferay.portal.dao.orm.hibernate.LongType" />
		<property access="com.liferay.portal.dao.orm.hibernate.LiferayPropertyAccessor" column="active_" name="active" type="com.liferay.portal.dao.orm.hibernate.BooleanType" />
		<property access="com.liferay.portal.dao.orm.hibernate.LiferayPropertyAccessor" name="startDate" type="org.hibernate.type.TimestampType" />
		<property access="com.liferay.portal.dao.orm.hibernate.LiferayPropertyAccessor" name="deleteDate" type="org.hibernate.type.TimestampType" />
		<property access="com.liferay.portal.dao.orm.hibernate.LiferayPropertyAccessor" name="createDate" type="org.hibernate.type.TimestampType" />
		<property access="com.liferay.portal.dao.orm.hibernate.LiferayPropertyAccessor" name="modifiedDate" type="org.hibernate.type.TimestampType" />
	</class>
	<class name="com.canal.etico.liferay.portlet.canal.manager.model.impl.ComunicacionImpl" table="canal_etico_Comunicacion">
		<id access="com.liferay.portal.dao.orm.hibernate.LiferayPropertyAccessor" name="comunicacionId" type="long">
			<generator class="assigned" />
		</id>
		<property access="com.liferay.portal.dao.orm.hibernate.LiferayPropertyAccessor" name="denunciaId" type="com.liferay.portal.dao.orm.hibernate.LongType" />
		<property access="com.liferay.portal.dao.orm.hibernate.LiferayPropertyAccessor" name="userId" type="com.liferay.portal.dao.orm.hibernate.LongType" />
		<property access="com.liferay.portal.dao.orm.hibernate.LiferayPropertyAccessor" name="descripcion" type="com.liferay.portal.dao.orm.hibernate.StringType" />
		<property access="com.liferay.portal.dao.orm.hibernate.LiferayPropertyAccessor" name="adjunto" type="com.liferay.portal.dao.orm.hibernate.LongType" />
		<property access="com.liferay.portal.dao.orm.hibernate.LiferayPropertyAccessor" name="observaciones" type="com.liferay.portal.dao.orm.hibernate.StringType" />
		<property access="com.liferay.portal.dao.orm.hibernate.LiferayPropertyAccessor" name="createDate" type="org.hibernate.type.TimestampType" />
		<property access="com.liferay.portal.dao.orm.hibernate.LiferayPropertyAccessor" name="modifiedDate" type="org.hibernate.type.TimestampType" />
	</class>
	<class name="com.canal.etico.liferay.portlet.canal.manager.model.impl.DenunciaImpl" table="canal_etico_Denuncia">
		<id access="com.liferay.portal.dao.orm.hibernate.LiferayPropertyAccessor" name="denunciaId" type="long">
			<generator class="assigned" />
		</id>
		<property access="com.liferay.portal.dao.orm.hibernate.LiferayPropertyAccessor" name="codigo" type="com.liferay.portal.dao.orm.hibernate.StringType" />
		<property access="com.liferay.portal.dao.orm.hibernate.LiferayPropertyAccessor" name="cif" type="com.liferay.portal.dao.orm.hibernate.StringType" />
		<property access="com.liferay.portal.dao.orm.hibernate.LiferayPropertyAccessor" name="compId" type="com.liferay.portal.dao.orm.hibernate.LongType" />
		<property access="com.liferay.portal.dao.orm.hibernate.LiferayPropertyAccessor" name="vinculacion" type="com.liferay.portal.dao.orm.hibernate.StringType" />
		<property access="com.liferay.portal.dao.orm.hibernate.LiferayPropertyAccessor" name="email" type="com.liferay.portal.dao.orm.hibernate.StringType" />
		<property access="com.liferay.portal.dao.orm.hibernate.LiferayPropertyAccessor" name="nombre" type="com.liferay.portal.dao.orm.hibernate.StringType" />
		<property access="com.liferay.portal.dao.orm.hibernate.LiferayPropertyAccessor" name="apellidos" type="com.liferay.portal.dao.orm.hibernate.StringType" />
		<property access="com.liferay.portal.dao.orm.hibernate.LiferayPropertyAccessor" name="nif" type="com.liferay.portal.dao.orm.hibernate.StringType" />
		<property access="com.liferay.portal.dao.orm.hibernate.LiferayPropertyAccessor" name="telefono" type="com.liferay.portal.dao.orm.hibernate.StringType" />
		<property access="com.liferay.portal.dao.orm.hibernate.LiferayPropertyAccessor" name="anonimo" type="com.liferay.portal.dao.orm.hibernate.BooleanType" />
		<property access="com.liferay.portal.dao.orm.hibernate.LiferayPropertyAccessor" name="tipo" type="com.liferay.portal.dao.orm.hibernate.LongType" />
		<property access="com.liferay.portal.dao.orm.hibernate.LiferayPropertyAccessor" name="categoria" type="com.liferay.portal.dao.orm.hibernate.LongType" />
		<property access="com.liferay.portal.dao.orm.hibernate.LiferayPropertyAccessor" name="asunto" type="com.liferay.portal.dao.orm.hibernate.StringType" />
		<property access="com.liferay.portal.dao.orm.hibernate.LiferayPropertyAccessor" name="descripcion" type="com.liferay.portal.dao.orm.hibernate.StringType" />
		<property access="com.liferay.portal.dao.orm.hibernate.LiferayPropertyAccessor" name="estado" type="com.liferay.portal.dao.orm.hibernate.LongType" />
		<property access="com.liferay.portal.dao.orm.hibernate.LiferayPropertyAccessor" name="motivoId" type="com.liferay.portal.dao.orm.hibernate.LongType" />
		<property access="com.liferay.portal.dao.orm.hibernate.LiferayPropertyAccessor" name="observaciones" type="com.liferay.portal.dao.orm.hibernate.StringType" />
		<property access="com.liferay.portal.dao.orm.hibernate.LiferayPropertyAccessor" name="createDate" type="org.hibernate.type.TimestampType" />
		<property access="com.liferay.portal.dao.orm.hibernate.LiferayPropertyAccessor" name="modifiedDate" type="org.hibernate.type.TimestampType" />
		<property access="com.liferay.portal.dao.orm.hibernate.LiferayPropertyAccessor" name="endDate" type="org.hibernate.type.TimestampType" />
	</class>
	<class name="com.canal.etico.liferay.portlet.canal.manager.model.impl.DenunciaAccionImpl" table="canal_etico_DenunciaAccion">
		<id access="com.liferay.portal.dao.orm.hibernate.LiferayPropertyAccessor" name="denunciaAccionId" type="long">
			<generator class="assigned" />
		</id>
		<property access="com.liferay.portal.dao.orm.hibernate.LiferayPropertyAccessor" name="denunciaId" type="com.liferay.portal.dao.orm.hibernate.LongType" />
		<property access="com.liferay.portal.dao.orm.hibernate.LiferayPropertyAccessor" name="accionId" type="com.liferay.portal.dao.orm.hibernate.LongType" />
		<property access="com.liferay.portal.dao.orm.hibernate.LiferayPropertyAccessor" name="userId" type="com.liferay.portal.dao.orm.hibernate.LongType" />
		<property access="com.liferay.portal.dao.orm.hibernate.LiferayPropertyAccessor" name="observaciones" type="com.liferay.portal.dao.orm.hibernate.StringType" />
		<property access="com.liferay.portal.dao.orm.hibernate.LiferayPropertyAccessor" name="createDate" type="org.hibernate.type.TimestampType" />
		<property access="com.liferay.portal.dao.orm.hibernate.LiferayPropertyAccessor" name="modifiedDate" type="org.hibernate.type.TimestampType" />
	</class>
	<class name="com.canal.etico.liferay.portlet.canal.manager.model.impl.MotivoImpl" table="canal_etico_Motivo">
		<id access="com.liferay.portal.dao.orm.hibernate.LiferayPropertyAccessor" name="motivoId" type="long">
			<generator class="assigned" />
		</id>
		<property access="com.liferay.portal.dao.orm.hibernate.LiferayPropertyAccessor" name="compId" type="com.liferay.portal.dao.orm.hibernate.LongType" />
		<property access="com.liferay.portal.dao.orm.hibernate.LiferayPropertyAccessor" name="nombre" type="com.liferay.portal.dao.orm.hibernate.StringType" />
		<property access="com.liferay.portal.dao.orm.hibernate.LiferayPropertyAccessor" name="observaciones" type="com.liferay.portal.dao.orm.hibernate.StringType" />
		<property access="com.liferay.portal.dao.orm.hibernate.LiferayPropertyAccessor" name="activo" type="com.liferay.portal.dao.orm.hibernate.BooleanType" />
		<property access="com.liferay.portal.dao.orm.hibernate.LiferayPropertyAccessor" name="createDate" type="org.hibernate.type.TimestampType" />
		<property access="com.liferay.portal.dao.orm.hibernate.LiferayPropertyAccessor" name="modifiedDate" type="org.hibernate.type.TimestampType" />
	</class>
	<class name="com.canal.etico.liferay.portlet.canal.manager.model.impl.ObservacionImpl" table="canal_etico_Observacion">
		<id access="com.liferay.portal.dao.orm.hibernate.LiferayPropertyAccessor" name="observacionId" type="long">
			<generator class="assigned" />
		</id>
		<property access="com.liferay.portal.dao.orm.hibernate.LiferayPropertyAccessor" name="denunciaId" type="com.liferay.portal.dao.orm.hibernate.LongType" />
		<property access="com.liferay.portal.dao.orm.hibernate.LiferayPropertyAccessor" name="userId" type="com.liferay.portal.dao.orm.hibernate.LongType" />
		<property access="com.liferay.portal.dao.orm.hibernate.LiferayPropertyAccessor" name="descripcion" type="com.liferay.portal.dao.orm.hibernate.StringType" />
		<property access="com.liferay.portal.dao.orm.hibernate.LiferayPropertyAccessor" name="createDate" type="org.hibernate.type.TimestampType" />
		<property access="com.liferay.portal.dao.orm.hibernate.LiferayPropertyAccessor" name="modifiedDate" type="org.hibernate.type.TimestampType" />
	</class>
	<class name="com.canal.etico.liferay.portlet.canal.manager.model.impl.UserCompanyImpl" table="canal_etico_UserCompany">
		<composite-id class="com.canal.etico.liferay.portlet.canal.manager.service.persistence.UserCompanyPK" name="primaryKey">
			<key-property access="com.liferay.portal.dao.orm.hibernate.LiferayPropertyAccessor" name="userId" type="com.liferay.portal.dao.orm.hibernate.LongType" />
			<key-property access="com.liferay.portal.dao.orm.hibernate.LiferayPropertyAccessor" name="compId" type="com.liferay.portal.dao.orm.hibernate.LongType" />
		</composite-id>
		<property access="com.liferay.portal.dao.orm.hibernate.LiferayPropertyAccessor" name="createDate" type="org.hibernate.type.TimestampType" />
		<property access="com.liferay.portal.dao.orm.hibernate.LiferayPropertyAccessor" name="modifiedDate" type="org.hibernate.type.TimestampType" />
		<property access="com.liferay.portal.dao.orm.hibernate.LiferayPropertyAccessor" name="deleteDate" type="org.hibernate.type.TimestampType" />
	</class>
	<class name="com.canal.etico.liferay.portlet.canal.manager.model.impl.VinculacionImpl" table="canal_etico_Vinculacion">
		<id access="com.liferay.portal.dao.orm.hibernate.LiferayPropertyAccessor" name="vinculacionId" type="long">
			<generator class="assigned" />
		</id>
		<property access="com.liferay.portal.dao.orm.hibernate.LiferayPropertyAccessor" name="compId" type="com.liferay.portal.dao.orm.hibernate.LongType" />
		<property access="com.liferay.portal.dao.orm.hibernate.LiferayPropertyAccessor" name="nombre" type="com.liferay.portal.dao.orm.hibernate.StringType" />
		<property access="com.liferay.portal.dao.orm.hibernate.LiferayPropertyAccessor" name="activo" type="com.liferay.portal.dao.orm.hibernate.BooleanType" />
		<property access="com.liferay.portal.dao.orm.hibernate.LiferayPropertyAccessor" name="createDate" type="org.hibernate.type.TimestampType" />
		<property access="com.liferay.portal.dao.orm.hibernate.LiferayPropertyAccessor" name="modifiedDate" type="org.hibernate.type.TimestampType" />
	</class>
</hibernate-mapping>